audiolazy/__init__.py
audiolazy/_internals.py
audiolazy/lazy_analysis.py
audiolazy/lazy_auditory.py
audiolazy/lazy_compat.py
audiolazy/lazy_core.py
audiolazy/lazy_filters.py
audiolazy/lazy_io.py
audiolazy/lazy_itertools.py
audiolazy/lazy_lpc.py
audiolazy/lazy_math.py
audiolazy/lazy_midi.py
audiolazy/lazy_misc.py
audiolazy/lazy_poly.py
audiolazy/lazy_stream.py
audiolazy/lazy_synth.py
audiolazy/lazy_text.py
audiolazy/lazy_wav.py
audiolazy-0.6.dist-info/DESCRIPTION.rst
audiolazy-0.6.dist-info/METADATA
audiolazy-0.6.dist-info/RECORD
audiolazy-0.6.dist-info/WHEEL
audiolazy-0.6.dist-info/metadata.json
audiolazy-0.6.dist-info/top_level.txt
